<mdRecord xmlns="http://dplava.lib.virginia.edu"
    xmlns:xsi="http://www.w3.org/2001/XMLSchema-instance"
    xmlns:dc="http://purl.org/dc/elements/1.1/" xmlns:dcterms="http://purl.org/dc/terms/"
    xmlns:edm="http://www.europeana.eu/schemas/edm/"
    xsi:schemaLocation="http://dplava.lib.virginia.edu
dplava.xsd">

    <dcterms:identifier>sfdst007009</dcterms:identifier>
    <dcterms:title>Cave Spring Memorandums, September 1942</dcterms:title>
    <dcterms:description>1942 Cave Spring Mutual Aid Disagreement and Fire Station Proposal, written/typed up in September of 1942 between Salem Fire Department and the Roanoke County Board of Supervisors on deciding the location of a fire department for the Cave Spring district.</dcterms:description>
    <dcterms:language>eng</dcterms:language>
    <dcterms:subject>Fire departments</dcterms:subject>
    <dcterms:subject>Virginia</dcterms:subject>
    <dcterms:type>Text</dcterms:type>
    <dcterms:spatial>Salem, Virginia, United States</dcterms:spatial>
    <dcterms:medium>memorandums</dcterms:medium>
    <dcterms:rights>http://rightsstatements.org/vocab/InC-EDU/1.0/</dcterms:rights>
    <dcterms:provenance>Virginia Polytechnic Institute and State University. University Libraries</dcterms:provenance>
    <edm:isShownAt>https://federated-pprd.d3reyduta3lkkz.amplifyapp.com/archive/hd24pp85</edm:isShownAt>
    <edm:preview>https://d21nnzi4oh5qvs.cloudfront.net/federated/sfd/tiles/sfdst007009-1/full/250,/0/default.jpg</edm:preview>
    <dcterms:date>2024-06-03T20:49:35.625Z</dcterms:date>
</mdRecord>