<mdRecord xmlns="http://dplava.lib.virginia.edu"
    xmlns:xsi="http://www.w3.org/2001/XMLSchema-instance"
    xmlns:dc="http://purl.org/dc/elements/1.1/" xmlns:dcterms="http://purl.org/dc/terms/"
    xmlns:edm="http://www.europeana.eu/schemas/edm/"
    xsi:schemaLocation="http://dplava.lib.virginia.edu
dplava.xsd">

    <dcterms:identifier>fchs_2006_010_1128</dcterms:identifier>
    <dcterms:title>Maple at Aunt J's House</dcterms:title>
    <dcterms:description>Maple Tree removed to make way for library through the seasons</dcterms:description>
    <dcterms:subject>Maple</dcterms:subject>
    <dcterms:medium>photographs</dcterms:medium>
    <dcterms:rights>http://rightsstatements.org/vocab/InC-NC/1.0/</dcterms:rights>
    <dcterms:provenance>Jessie T. Heafner Photographic Collection CG 0008</dcterms:provenance>
    <dcterms:provenance>Virginia Polytechnic Institute and State University. University Libraries</dcterms:provenance>
    <edm:isShownAt>https://federated-pprd.d3reyduta3lkkz.amplifyapp.com/archive/2m16zh4g</edm:isShownAt>
    <edm:preview>https://d21nnzi4oh5qvs.cloudfront.net/federated/FCHS/FCHS_PHO/tiles/fchs_2006_010_1128-1/full/203,/0/default.jpg</edm:preview>
    <dcterms:date>2024-10-11T15:35:22.063Z</dcterms:date>
</mdRecord>