<mdRecord xmlns:dc="http://purl.org/dc/elements/1.1/"
    xmlns:dcterms="http://purl.org/dc/terms/"
    xmlns:rdf="http://www.w3.org/1999/02/22-rdf-syntax-ns#"
    xmlns:edm="http://www.europeana.eu/schemas/edm/"
    xmlns="http://dplava.lib.virginia.edu"
    xmlns:xsi="http://www.w3.org/2001/XMLSchema-instance"
    xsi:schemaLocation="http://dplava.lib.virginia.edu dplava.xsd">

    <dcterms:identifier>MTG_RNJ_002436</dcterms:identifier>
    <dcterms:title>Radford News Journal (East Radford, VA), 69th Year, No. 14, Monday, February 18, 1952</dcterms:title>
    <dcterms:description>Afternoon newspaper from Radford, Virginia that includes global, national, and local news and advertisements.</dcterms:description>
    <dcterms:isPartOf>MTG</dcterms:isPartOf>
    <dcterms:provenance>Virginia Polytechnic Institute and State University. University Libraries</dcterms:provenance>
    <edm:isShownAt>https://federated-pprd.d3reyduta3lkkz.amplifyapp.com/archive/gz774s8r</edm:isShownAt>
    <edm:preview>https://img.cloud.lib.vt.edu/swva/MTG/tiles/MTG_RNJ_002436-1/full/199,/0/default.jpg</edm:preview>
</mdRecord>